dt4test/__init__.py
dt4test/bin/dt
dt4test/lib/__init__.py
dt4test/lib/base.py
dt4test/lib/case_runner.py
dt4test/lib/config_ini.py
dt4test/lib/element.py
dt4test/lib/expectation.py
dt4test/lib/helper.py
dt4test/lib/jsonp.py
dt4test/lib/logger.py
dt4test/lib/network.py
dt4test/lib/operating_system.py
dt4test/lib/process.py
dt4test/monitor/cpu_idle.sh
dt4test/monitor/mem_usage.sh
dt4test/monitor/monitor_conf.ini
dt4test/resource/__init__.py
dt4test/resource/env.py
dt4test/resource/monitor.py
dt4test/resource/perform.py
dt4test/resource/poster.py
dt4test/resource/resource.py
dt4test/resource/resource_template.py
dt4test/resource/time_server.py
dt4test/resource/time_server_checkrule.py
dt4test/resource/time_server_serviceproxy.py
dt4test/resource/zookeeper.py
dt4test/tests/__init__.py
dt4test/tests/test_base.py
dt4test/tests/test_network.py
dt4test/tests/test_os.py
dt4test/tests/test_perform.py
dt4test/tests/test_poster.py
dt4test/tests/test_time_server.py
dt4test/webui/__init__.py
dt4test/webui/app.py
dt4test/webui/auto/__init__.py
dt4test/webui/auto/configuration.py
dt4test/webui/auto/exceptions.py
dt4test/webui/auto/settings.py
dt4test/webui/auto/version.py
dt4test/webui/auto/www/__init__.py
dt4test/webui/auto/www/app.py
dt4test/webui/auto/www/blueprints.py
dt4test/webui/auto/www/api/__init__.py
dt4test/webui/auto/www/api/auth.py
dt4test/webui/auto/www/api/case.py
dt4test/webui/auto/www/api/cia.py
dt4test/webui/auto/www/api/cia_file.py
dt4test/webui/auto/www/api/editor.py
dt4test/webui/auto/www/api/keyword.py
dt4test/webui/auto/www/api/manage_file.py
dt4test/webui/auto/www/api/project.py
dt4test/webui/auto/www/api/report.py
dt4test/webui/auto/www/api/settings.py
dt4test/webui/auto/www/api/settings_ORG.py
dt4test/webui/auto/www/api/suite.py
dt4test/webui/auto/www/api/task.py
dt4test/webui/auto/www/api/tasklist.py
dt4test/webui/auto/www/api/test_design.py
dt4test/webui/auto/www/api/time_server.py
dt4test/webui/auto/www/api/time_server_checkrule.py
dt4test-0.3.1.dist-info/METADATA
dt4test-0.3.1.dist-info/WHEEL
dt4test-0.3.1.dist-info/top_level.txt
dt4test-0.3.1.dist-info/RECORD
