Metadata-Version: 2.1
Name: dt4test
Version: 0.3.1
Summary: 通用后台分布式测试库 集成多种测试工具及整合各种后台命令
Home-page: https://dt4test.readthedocs.io/
Download-URL: https://pypi.org/project/dt4test/
Author: wentao ma
Author-email: mawentao119@gmail.com
License: Apache License 2.0
Keywords: dt4test automation testautomation rpa testing acceptancetesting atdd bdd
Platform: any
Classifier: Development Status :: 5 - Production/Stable
Classifier: License :: OSI Approved :: Apache Software License
Classifier: Operating System :: OS Independent
Classifier: Programming Language :: Python :: 3
Classifier: Programming Language :: Python :: 3 :: Only
Classifier: Programming Language :: Python :: 3.6
Classifier: Programming Language :: Python :: 3.7
Classifier: Programming Language :: Python :: 3.8
Classifier: Programming Language :: Python :: 3.9
Classifier: Programming Language :: Python :: 3.10
Classifier: Programming Language :: Python :: Implementation :: CPython
Classifier: Programming Language :: Python :: Implementation :: PyPy
Classifier: Topic :: Software Development :: Testing
Classifier: Topic :: Software Development :: Testing :: Acceptance
Classifier: Topic :: Software Development :: Testing :: BDD
Classifier: Framework :: Robot Framework
Requires-Python: >=3.6
Requires-Dist: Flask
Requires-Dist: Flask-APScheduler
Requires-Dist: Flask-RESTful
Requires-Dist: markdown
Requires-Dist: openpyxl
Requires-Dist: pytest
Requires-Dist: jmespath
Requires-Dist: paramiko
Requires-Dist: robotframework
Requires-Dist: kazoo
Requires-Dist: requests
Requires-Dist: GitPython
Requires-Dist: pyyaml
